chopshop/ChopShop.py
chopshop/__init__.py
chopshop/audio/__init__.py
chopshop/audio/convert_to_wav.py
chopshop/audio/diarize_with_thirdparty.py
chopshop/audio/extract_wav_from_video.py
chopshop/audio/extract_whisper_embeddings.py
chopshop/audio/extract_whisper_embeddings_subproc.py
chopshop/audio/split_wav_by_speaker.py
chopshop/audio/diarizer/__init__.py
chopshop/audio/diarizer/whisper_diar_wrapper.py
chopshop/audio/diarizer/whisper-diarization/__init__.py
chopshop/audio/diarizer/whisper-diarization/diarize.py
chopshop/audio/diarizer/whisper-diarization/diarize_custom.py
chopshop/audio/diarizer/whisper-diarization/diarize_parallel.py
chopshop/audio/diarizer/whisper-diarization/helpers.py
chopshop/audio/diarizer/whisper-diarization/diarization/__init__.py
chopshop/audio/diarizer/whisper-diarization/diarization/msdd/msdd.py
chopshop/helpers/__init__.py
chopshop/helpers/feature_gather.py
chopshop/helpers/find_files.py
chopshop/helpers/text_gather.py
chopshop/pipelines/__init__.py
chopshop/pipelines/run_pipeline.py
chopshop/text/analyze_with_archetypes.py
chopshop/text/analyze_with_dictionaries.py
chopshop/text/extract_sentence_embeddings.py
chopshop/text/dictionary_analyzers/__init__.py
chopshop/text/dictionary_analyzers/multi_archetype_analyzer.py
chopshop/text/dictionary_analyzers/multi_dict_analyzer.py
chopshop/video/__init__.py
chopshop/video/extract_features.py
chopshop/video/features_basic.py
chopshop/video/features_motion.py
chopshop/video/features_ocr.py
chopshop/video/features_shots.py
chopshop/video/read_video.py
chopshop/video/windowing.py
chopshop-0.0.6.dist-info/licenses/LICENSE
chopshop-0.0.6.dist-info/METADATA
chopshop-0.0.6.dist-info/WHEEL
chopshop-0.0.6.dist-info/entry_points.txt
chopshop-0.0.6.dist-info/top_level.txt
chopshop-0.0.6.dist-info/RECORD
