Metadata-Version: 2.4
Name: chopshop
Version: 0.0.6
Summary: Audio/video chop → analyze toolkit.
Author-email: "Ryan L. Boyd" <ryan@ryanboyd.io>
License: MIT
Project-URL: Homepage, https://github.com/ryanboyd/chopshop
Project-URL: Issues, https://github.com/ryanboyd/chopshop/issues
Classifier: Programming Language :: Python :: 3
Classifier: License :: OSI Approved :: MIT License
Classifier: Operating System :: OS Independent
Classifier: Topic :: Multimedia :: Sound/Audio :: Analysis
Classifier: Intended Audience :: Science/Research
Requires-Python: >=3.10
License-File: LICENSE
Requires-Dist: faster-whisper>=1.1.0
Requires-Dist: transformers>=4.38.0
Requires-Dist: librosa>=0.10.1
Requires-Dist: pydub>=0.25.1
Requires-Dist: contentcoder
Requires-Dist: archetyper
Requires-Dist: nltk
Requires-Dist: sentence-transformers
Provides-Extra: diarization
Requires-Dist: nemo-toolkit[asr]>=2.dev; extra == "diarization"
Provides-Extra: cuda
Requires-Dist: nvidia-cudnn-cu12; extra == "cuda"
Dynamic: license-file
